{
	"animations": [
		{
			"loop": false,
			"offsets": [
				0,
				-9
			],
			"anim": "danceLeft",
			"fps": 24,
			"name": "gfleft",
			"indices": []
		},
		{
			"loop": false,
			"offsets": [
				0,
				-9
			],
			"anim": "danceRight",
			"fps": 24,
			"name": "gfright",
			"indices": []
		},
		{
			"loop": false,
			"offsets": [
				3,
				-9
			],
			"anim": "cheer",
			"fps": 24,
			"name": "gfcheer",
			"indices": []
		}
	],
	"no_antialiasing": false,
	"image": "characters/gf_berserk",
	"position": [
		-40,
		-60
	],
	"healthicon": "gf",
	"flip_x": false,
	"healthbar_colors": [
		165,
		0,
		77
	],
	"camera_position": [
		0,
		0
	],
	"sing_duration": 4,
	"scale": 1.3
}